nonebot_plugin_r6s/__init__.py
nonebot_plugin_r6s/fonts/GenYoMin-M.ttc
nonebot_plugin_r6s/fonts/LICENSE_OFL.txt
nonebot_plugin_r6s/fonts/SIL_Open_Font_License_1.1.txt
nonebot_plugin_r6s/image.py
nonebot_plugin_r6s/imgs/avatar/default_146_146.png
nonebot_plugin_r6s/imgs/operators/Ace.png
nonebot_plugin_r6s/imgs/operators/Alibi.png
nonebot_plugin_r6s/imgs/operators/Amaru.png
nonebot_plugin_r6s/imgs/operators/Aruni.png
nonebot_plugin_r6s/imgs/operators/Ash.png
nonebot_plugin_r6s/imgs/operators/Bandit.png
nonebot_plugin_r6s/imgs/operators/Blackbeard.png
nonebot_plugin_r6s/imgs/operators/Blitz.png
nonebot_plugin_r6s/imgs/operators/Buck.png
nonebot_plugin_r6s/imgs/operators/Capitão.png
nonebot_plugin_r6s/imgs/operators/Castle.png
nonebot_plugin_r6s/imgs/operators/Caveira.png
nonebot_plugin_r6s/imgs/operators/Clash.png
nonebot_plugin_r6s/imgs/operators/Doc.png
nonebot_plugin_r6s/imgs/operators/Dokkaebi.png
nonebot_plugin_r6s/imgs/operators/Echo.png
nonebot_plugin_r6s/imgs/operators/Ela.png
nonebot_plugin_r6s/imgs/operators/Finka.png
nonebot_plugin_r6s/imgs/operators/Flores.png
nonebot_plugin_r6s/imgs/operators/Frost.png
nonebot_plugin_r6s/imgs/operators/Fuze.png
nonebot_plugin_r6s/imgs/operators/Glaz.png
nonebot_plugin_r6s/imgs/operators/Goyo.png
nonebot_plugin_r6s/imgs/operators/Gridlock.png
nonebot_plugin_r6s/imgs/operators/Hibana.png
nonebot_plugin_r6s/imgs/operators/Iana.png
nonebot_plugin_r6s/imgs/operators/IQ.png
nonebot_plugin_r6s/imgs/operators/Jackal.png
nonebot_plugin_r6s/imgs/operators/Jäger.png
nonebot_plugin_r6s/imgs/operators/Kaid.png
nonebot_plugin_r6s/imgs/operators/Kali.png
nonebot_plugin_r6s/imgs/operators/Kapkan.png
nonebot_plugin_r6s/imgs/operators/Lesion.png
nonebot_plugin_r6s/imgs/operators/Lion.png
nonebot_plugin_r6s/imgs/operators/Maestro.png
nonebot_plugin_r6s/imgs/operators/Maverick.png
nonebot_plugin_r6s/imgs/operators/Melusi.png
nonebot_plugin_r6s/imgs/operators/Mira.png
nonebot_plugin_r6s/imgs/operators/Montagne.png
nonebot_plugin_r6s-0.4.2.dist-info/LICENSE
nonebot_plugin_r6s-0.4.2.dist-info/WHEEL
nonebot_plugin_r6s-0.4.2.dist-info/METADATA
nonebot_plugin_r6s-0.4.2.dist-info/RECORD
