Metadata-Version: 2.1
Name: nonebot-plugin-r6s
Version: 0.4.2
Summary: A R6s plugin for Nonebot2
Home-page: https://github.com/abrahum/nonebot_plugin_r6s
License: GPLv3
Keywords: nonebot,nonebot2,r6s
Author: abrahumlink
Author-email: 307887491@qq.com
Requires-Python: >=3.7.3,<4.0.0
Classifier: License :: Other/Proprietary License
Classifier: Programming Language :: Python :: 3
Classifier: Programming Language :: Python :: 3.10
Classifier: Programming Language :: Python :: 3.8
Classifier: Programming Language :: Python :: 3.9
Requires-Dist: Pillow (>=8.4.0,<9.0.0)
Requires-Dist: httpx (>=0.21.1,<1.0.0)
Requires-Dist: nonebot-adapter-onebot (>=2.0.0-beta.1,<3.0.0)
Requires-Dist: nonebot2 (>=2.0.0-beta.1,<3.0.0)
Requires-Dist: ujson (>=4.0.2,<5.0.0)
Project-URL: Documentation, https://github.com/abrahum/nonebot_plugin_r6s#readme
